genkey/__init__.py
genkey/main.py
genkey-0.1.0.dist-info/LICENSE
genkey-0.1.0.dist-info/METADATA
genkey-0.1.0.dist-info/WHEEL
genkey-0.1.0.dist-info/entry_points.txt
genkey-0.1.0.dist-info/top_level.txt
genkey-0.1.0.dist-info/RECORD
