Metadata-Version: 2.1
Name: genkey
Version: 0.1.0
Summary: A simple command-line tool to generate secure keys and passwords
Home-page: https://github.com/dawid-ai/genkey
Author: [Your Name]
Author-email: dawid-ai <hello@dawid.ai>
License: MIT License
Classifier: Programming Language :: Python :: 3
Classifier: License :: OSI Approved :: MIT License
Classifier: Operating System :: OS Independent
Classifier: Environment :: Console
Classifier: Intended Audience :: Developers
Classifier: Topic :: Security :: Cryptography
Requires-Python: >=3.6
License-File: LICENSE
